README.txt
setup.py
QtViews.egg-info/PKG-INFO
QtViews.egg-info/SOURCES.txt
QtViews.egg-info/dependency_links.txt
QtViews.egg-info/top_level.txt
qtviews/__init__.py
qtviews/calendar.py
qtviews/dockers.py
qtviews/htmldelegate.py
qtviews/utils.py