Metadata-Version: 1.1
Name: QtViews
Version: 0.3.0
Summary: QtViews Library for Qt Helpers
Home-page: https://bitbucket.org/jbmohler/qtviews/
Author: Joel B. Mohler
Author-email: joel@kiwistrawberry.us
License: LGPLv2+
Platform: UNKNOWN
Classifier: Development Status :: 4 - Beta
Classifier: Intended Audience :: Developers
Classifier: License :: OSI Approved :: GNU Lesser General Public License v2 (LGPLv2)
Classifier: Programming Language :: Python :: 2
Classifier: Programming Language :: Python :: 3
Classifier: Operating System :: OS Independent
Classifier: Environment :: Win32 (MS Windows)
Classifier: Environment :: X11 Applications :: Qt
